transpak/SerialReader.py
transpak/__init__.py
transpak/pak_lib.py
transpak/v1.py
transpak/v4.py
transpak-0.3.dist-info/LICENSE
transpak-0.3.dist-info/WHEEL
transpak-0.3.dist-info/METADATA
transpak-0.3.dist-info/RECORD
