Metadata-Version: 2.1
Name: transpak
Version: 0.3
Summary: Binary packaging and compression library for PQM-800 transient data 
Author: Christoph Kattmann
Author-email: christoph.kattmann@bss-hs.de
Classifier: License :: OSI Approved :: GNU General Public License v3 or later (GPLv3+)
